<?xml version="1.0" encoding="UTF-8"?>
<entry xmlns="http://www.w3.org/2005/Atom" xmlns:dcterms="http://purl.org/dc/terms" xmlns:xhtml="http://www.w3.org/1999/xhtml">
  <title>The Death of Ivan Ilyich and Other Stories</title>
  <id>urn:book:14c5310f-fbf3-404a-956c-7ac160414da0</id>
  <updated>2020-03-28T08:02:50Z</updated>
  <link href="./book_568.xml" type="application/atom+xml;type=entry;profile=opds-catalog" rel="self" title="The Death of Ivan Ilyich and Other Stories" />
  <link href="../index.xml" type="application/atom+xml;profile=opds-catalog;kind=navigation" rel="start" title="Arjun Srivastava's Library " />
  <link href="../index.xml" type="application/atom+xml;profile=opds-catalog;kind=navigation" rel="breadcrumb" title="Arjun Srivastava's Library " />
  <link href="../authorlist/authorlist_Page_1.xml" type="application/atom+xml;profile=opds-catalog;kind=navigation" rel="breadcrumb" title="Authors" />
  <link href="../authorlist/authorlist_L_Page_1.xml" type="application/atom+xml;profile=opds-catalog;kind=navigation" rel="breadcrumb" title="Authors starting with L" />
  <link href="https://raw.githubusercontent.com/arjunbazinga/books/master/Leo%20Tolstoy/The%20Death%20of%20Ivan%20Ilyich%20and%20Other%20Stories%20%28568%29/c2o_resizedcover.jpg" type="image/jpg" rel="http://opds-spec.org/image" />
  <link href="https://raw.githubusercontent.com/arjunbazinga/books/master/Leo%20Tolstoy/The%20Death%20of%20Ivan%20Ilyich%20and%20Other%20Stories%20%28568%29/c2o_thumbnail.jpg" type="image/jpg" rel="http://opds-spec.org/image/thumbnail" />
  <link href="https://raw.githubusercontent.com/arjunbazinga/books/master/Leo%20Tolstoy/The%20Death%20of%20Ivan%20Ilyich%20and%20Other%20Stories%20%28568%29/The%20Death%20of%20Ivan%20Ilyich%20and%20Other%20Stories%20-%20Leo%20Tolstoy.epub" type="application/epub+zip" rel="http://opds-spec.org/acquisition" title="Download this ebook as EPUB" />
  <link href="https://raw.githubusercontent.com/arjunbazinga/books/master/Leo%20Tolstoy/The%20Death%20of%20Ivan%20Ilyich%20and%20Other%20Stories%20%28568%29/The%20Death%20of%20Ivan%20Ilyich%20and%20Other%20Stories%20-%20Leo%20Tolstoy.pdf" type="application/pdf" rel="http://opds-spec.org/acquisition" title="Download this ebook as PDF" />
  <author>
    <name>Leo Tolstoy</name>
    <uri>../author_0/author_324_Page_1.xml</uri>
  </author>
  <published>0101-01-01T00:00:00Z</published>
  <dcterms:language>en</dcterms:language>
  <dcterms:publisher>Penguin USA, Inc.</dcterms:publisher>
  <category term="Lang:en" />
  <content type="text/html">
    <p>
      <strong>Rating:</strong>
      Not rated
    </p>
    <p>
      <strong>Tags:</strong>
      Lang:en
    </p>
    <p>
      <strong>Publisher:</strong>
      Penguin USA, Inc.
    </p>
    <p>
      <strong>Added:</strong>
      April 19, 2019
    </p>
    <p>
      <strong>Modified:</strong>
      March 28, 2020
    </p>
  </content>
  <link href="http://www.goodreads.com/book/title/The%20Death%20of%20Ivan%20Ilyich%20and%20Other%20Stories" type="text/html" rel="related" title="This book on Goodreads" />
  <link href="http://en.wikipedia.org/wiki/The%20Death%20of%20Ivan%20Ilyich%20and%20Other%20Stories" type="text/html" rel="related" title="This book on Wikipedia" />
  <link href="http://www.librarything.com/title/The%20Death%20of%20Ivan%20Ilyich%20and%20Other%20Stories%20Leo%20Tolstoy" type="text/html" rel="related" title="This book on LibraryThing" />
  <link href="http://www.amazon.com/gp/search/ref=sr_adv_b/?search-alias=stripbooks&amp;unfiltered=1&amp;sort=relevanceexprank&amp;field-title=The%20Death%20of%20Ivan%20Ilyich%20and%20Other%20Stories&amp;field-author=Leo%20Tolstoy" type="text/html" rel="related" title="This book on Amazon" />
  <link href="http://www.goodreads.com/book/author/Leo%20Tolstoy" type="text/html" rel="related" title="Leo Tolstoy on Goodreads" />
  <link href="http://en.wikipedia.org/wiki/Leo%20Tolstoy" type="text/html" rel="related" title="Leo Tolstoy on Wikipedia" />
  <link href="http://www.librarything.com/author/TolstoyLeo" type="text/html" rel="related" title="Leo Tolstoy on LibraryThing" />
  <link href="http://www.amazon.com/gp/search/ref=sr_adv_b/?search-alias=stripbooks&amp;unfiltered=1&amp;sort=relevanceexprank&amp;field-author=Leo%20Tolstoy" type="text/html" rel="related" title="Leo Tolstoy on Amazon" />
  <link href="http://www.isfdb.org/cgi-bin/ea.cgi?Leo%20Tolstoy" type="text/html" rel="related" title="Leo Tolstoy on ISFDB" />
</entry>
